vernacular_ai_speech-0.1.1-py3.7-nspkg.pth
vernacular/ai/exceptions/__init__.py
vernacular/ai/speech/__init__.py
vernacular/ai/speech/enums.py
vernacular/ai/speech/speech_client.py
vernacular/ai/speech/types.py
vernacular/ai/speech/utils.py
vernacular/ai/speech/proto/__init__.py
vernacular/ai/speech/proto/speech_to_text_pb2.py
vernacular/ai/speech/proto/speech_to_text_pb2_grpc.py
vernacular_ai_speech-0.1.1.dist-info/METADATA
vernacular_ai_speech-0.1.1.dist-info/WHEEL
vernacular_ai_speech-0.1.1.dist-info/namespace_packages.txt
vernacular_ai_speech-0.1.1.dist-info/top_level.txt
vernacular_ai_speech-0.1.1.dist-info/RECORD
