Metadata-Version: 2.1
Name: vernacular-ai-speech
Version: 0.1.1
Summary: Vernacular Speech API python client
Home-page: https://github.com/Vernacular-ai/speech-recognition
Author: Vernacular.ai
Author-email: deepankar@vernacular.ai
License: Apache 2.0
Platform: Posix; MacOS X; Windows
Classifier: Development Status :: 4 - Beta
Classifier: Intended Audience :: Developers
Classifier: Topic :: Software Development :: Build Tools
Classifier: License :: OSI Approved :: Apache Software License
Classifier: Programming Language :: Python
Classifier: Programming Language :: Python :: 3
Classifier: Programming Language :: Python :: 3.5
Classifier: Programming Language :: Python :: 3.6
Classifier: Programming Language :: Python :: 3.7
Classifier: Operating System :: OS Independent
Requires-Python: >=3.5
Requires-Dist: grpcio (>=1.27.1)
Requires-Dist: googleapis-common-protos (==1.51.0)
